{
  "_generated": "2026-06-30T23:00:05.793Z",
  "_matchCount": 6,
  "slotMatches": [
    "match_9",
    "match_1",
    "match_4",
    "match_10",
    "match_2"
  ],
  "participants": {
    "Yusuf Şahin": [
      true,
      false,
      true,
      true,
      true
    ],
    "Batu Balcı": [
      true,
      false,
      false,
      true,
      true
    ],
    "Emre Bulut": [
      true,
      true,
      true,
      false,
      false
    ],
    "Barış Başar": [
      true,
      false,
      true,
      true,
      true
    ],
    "Serhat Gürgenyatağı": [
      true,
      false,
      true,
      true,
      true
    ],
    "Burak Arslantürk": [
      false,
      false,
      true,
      true,
      true
    ],
    "Kuzey Emre": [
      true,
      false,
      true,
      true,
      true
    ],
    "Emin Balçın": [
      true,
      true,
      true,
      false,
      true
    ],
    "Berk Uzun": [
      false,
      false,
      true,
      true,
      true
    ],
    "Yiğit Yıldırım": [
      true,
      false,
      true,
      false,
      true
    ],
    "Enes Özşen": [
      false,
      false,
      true,
      false,
      true
    ],
    "Bahadır Seril": [
      true,
      false,
      true,
      false,
      true
    ],
    "Burak Onur Uysal": [
      true,
      false,
      false,
      true,
      true
    ],
    "Emir Çiftçi": [
      true,
      false,
      false,
      true,
      true
    ],
    "Talha Kılıç": [
      true,
      false,
      false,
      true,
      true
    ],
    "Bedirhan Çakır": [
      true,
      false,
      true,
      true,
      true
    ],
    "Batu Çataklı": [
      true,
      false,
      true,
      true,
      true
    ],
    "Demir Öztürk": [
      true,
      false,
      false,
      true,
      true
    ],
    "Mert Gürgenyatağı": [
      true,
      false,
      false,
      true,
      true
    ]
  }
}