{
  "_generated": "2026-07-15T21:02:38.785Z",
  "_numSims": 1000000,
  "_matchesPlayed": 30,
  "currentTopScore": 48,
  "participants": {
    "Yusuf Şahin": {
      "currentScore": 30,
      "peakPoss": 30,
      "avgPts": 30,
      "eliminated": true
    },
    "Batu Balcı": {
      "currentScore": 35,
      "peakPoss": 43,
      "avgPts": 39,
      "eliminated": true
    },
    "Emre Bulut": {
      "currentScore": 14,
      "peakPoss": 14,
      "avgPts": 14,
      "eliminated": true
    },
    "Barış Başar": {
      "currentScore": 35,
      "peakPoss": 43,
      "avgPts": 39,
      "eliminated": true
    },
    "Serhat Gürgenyatağı": {
      "currentScore": 48,
      "peakPoss": 56,
      "avgPts": 52,
      "eliminated": false
    },
    "Burak Arslantürk": {
      "currentScore": 44,
      "peakPoss": 44,
      "avgPts": 44,
      "eliminated": true
    },
    "Kuzey Emre": {
      "currentScore": 41,
      "peakPoss": 49,
      "avgPts": 45,
      "eliminated": false
    },
    "Emin Balçın": {
      "currentScore": 38,
      "peakPoss": 46,
      "avgPts": 42,
      "eliminated": true
    },
    "Berk Uzun": {
      "currentScore": 42,
      "peakPoss": 50,
      "avgPts": 46,
      "eliminated": false
    },
    "Yiğit Yıldırım": {
      "currentScore": 35,
      "peakPoss": 43,
      "avgPts": 39,
      "eliminated": true
    },
    "Enes Özşen": {
      "currentScore": 34,
      "peakPoss": 42,
      "avgPts": 38,
      "eliminated": true
    },
    "Bahadır Seril": {
      "currentScore": 25,
      "peakPoss": 25,
      "avgPts": 25,
      "eliminated": true
    },
    "Burak Onur Uysal": {
      "currentScore": 42,
      "peakPoss": 42,
      "avgPts": 42,
      "eliminated": true
    },
    "Emir Çiftçi": {
      "currentScore": 30,
      "peakPoss": 30,
      "avgPts": 30,
      "eliminated": true
    },
    "Talha Kılıç": {
      "currentScore": 34,
      "peakPoss": 34,
      "avgPts": 34,
      "eliminated": true
    },
    "Bedirhan Çakır": {
      "currentScore": 43,
      "peakPoss": 51,
      "avgPts": 47,
      "eliminated": false
    },
    "Batu Çataklı": {
      "currentScore": 37,
      "peakPoss": 37,
      "avgPts": 37,
      "eliminated": true
    },
    "Demir Öztürk": {
      "currentScore": 44,
      "peakPoss": 52,
      "avgPts": 48,
      "eliminated": false
    },
    "Mert Gürgenyatağı": {
      "currentScore": 35,
      "peakPoss": 35,
      "avgPts": 35,
      "eliminated": true
    }
  }
}